usls_mark/__init__.py
usls_mark/basics.py
usls_mark/bbox.py
usls_mark/class_manager.py
usls_mark/image_manager.py
usls_mark/keyboard.py
usls_mark/line_thickness.py
usls_mark/main.py
usls_mark/marker.py
usls_mark/model.py
usls_mark/mouse.py
usls_mark/palette.py
usls_mark/result.py
usls_mark-1.0.5.dist-info/LICENSE
usls_mark-1.0.5.dist-info/METADATA
usls_mark-1.0.5.dist-info/WHEEL
usls_mark-1.0.5.dist-info/entry_points.txt
usls_mark-1.0.5.dist-info/top_level.txt
usls_mark-1.0.5.dist-info/RECORD
