Metadata-Version: 2.1
Name: usls-mark
Version: 1.0.5
Summary: A useless image marker for object detection.
Author-email: jamjamjon <thisiszhangjian@qq.com>
License: GNU GENERAL PUBLIC LICENSE
Project-URL: Homepage, https://github.com/jamjamjon/usls-mark
Classifier: Programming Language :: Python :: 3
Requires-Python: >=3.8
License-File: LICENSE
Requires-Dist: numpy
Requires-Dist: opencv-python
Requires-Dist: onnxruntime
Requires-Dist: rich
